LICENSE
MANIFEST.in
setup.py
flask_mongo_sessions/__init__.py
flask_mongo_sessions.egg-info/PKG-INFO
flask_mongo_sessions.egg-info/SOURCES.txt
flask_mongo_sessions.egg-info/dependency_links.txt
flask_mongo_sessions.egg-info/not-zip-safe
flask_mongo_sessions.egg-info/requires.txt
flask_mongo_sessions.egg-info/top_level.txt
flask_mongo_sessions/tests/__init__.py
flask_mongo_sessions/tests/test_apps.py